pyGDM2/__init__.py
pyGDM2/core.py
pyGDM2/fields.py
pyGDM2/linear.py
pyGDM2/linear_py.py
pyGDM2/materials.py
pyGDM2/nonlinear.py
pyGDM2/propagators.py
pyGDM2/pyGDMfor.cp38-win_amd64.pyd
pyGDM2/structures.py
pyGDM2/tools.py
pyGDM2/visu.py
pyGDM2/visu3d.py
pyGDM2/EO/__init__.py
pyGDM2/EO/core.py
pyGDM2/EO/models.py
pyGDM2/EO/problems.py
pyGDM2/EO/tools.py
pyGDM2/EO1/__init__.py
pyGDM2/EO1/core.py
pyGDM2/EO1/models.py
pyGDM2/EO1/problems.py
pyGDM2/EO1/tools.py
pyGDM2-1.0.11.1.dist-info/LICENSE.txt
pyGDM2-1.0.11.1.dist-info/METADATA
pyGDM2-1.0.11.1.dist-info/WHEEL
pyGDM2-1.0.11.1.dist-info/top_level.txt
pyGDM2-1.0.11.1.dist-info/RECORD
