Metadata-Version: 2.1
Name: pyGDM2
Version: 1.0.11.1
Summary: A python full-field electrodynamical solver, based on the Green dyadic method (volume integral technique in frequency domain).
Home-page: https://gitlab.com/wiechapeter/pyGDM2
Author: Peter R. Wiecha
Author-email: wiechapeter@gmail.com
License: GPLv3+
Keywords: coupled dipoles method,green dyadic method,electrodynamical simulations,nano optics,frequency-domain
Platform: UNKNOWN
Classifier: Development Status :: 5 - Production/Stable
Classifier: Topic :: Scientific/Engineering :: Physics
Classifier: Environment :: Console
Classifier: Programming Language :: Python :: 2.7
Classifier: Programming Language :: Python :: 3.5
Classifier: Programming Language :: Python :: 3.6
Classifier: Programming Language :: Python :: 3.7
Classifier: License :: OSI Approved :: GNU General Public License v3 or later (GPLv3+)
Classifier: Intended Audience :: Science/Research
Requires-Python: >=2.7
Requires-Dist: numpy
